[
  {"id":"-MjWfwRjXzU","title":"Rs. 1.5 lakh for eating rice?","meta":"Nepal's first bhat eating competition","views":"258K views"},
  {"id":"kd9bzr4jbhc","title":"Rs. 10,000 biryani challenge","meta":"2KG biryani","views":"204K views"},
  {"id":"AYNEyEq5UQM","title":"Exposing KFC Nepal","meta":"Same chicken, different quality?","views":"119K views"},
  {"id":"9Jo5OTJrE6M","title":"Opening our own restaurant","meta":"The Second Plate · official tasting","views":"80K views"},
  {"id":"STYax0MZaCg","title":"Best keema noodles in Nepal","meta":"ft. The Second Plate · Ep 2","views":"70K views"},
  {"id":"TgjMPmF4DiY","title":"Best rice bowl in Kathmandu","meta":"ft. The Second Plate","views":"59K views"},
  {"id":"JZj5PwW9kks","title":"Spend Rs.10,000 in 24 hours","meta":"ft. Gurung Eating Channel"},
  {"id":"WKu2ZxZEH_I","title":"Worst copy of famous fast food","meta":"Honest taste test"},
  {"id":"yUe3ApluD7A","title":"5 best chicken dishes in Kathmandu","meta":"Momo, shawarma & more"},
  {"id":"IyTGvxnoYBM","title":"Budhanilkantha food hunt","meta":"Burgers, drumsticks & BBQ"},
  {"id":"dCeVv1eUZN0","title":"24 lucky subscribers at The Second Plate","meta":"Community day"},
  {"id":"X03cFbBNbi8","title":"Best sukuti in Kathmandu Valley","meta":"ft. Aashin Dangal"}
]
